src/__init__.py
src/version.py
src/agents/__init__.py
src/agents/base.py
src/agents/hed.py
src/agents/state.py
src/api/__init__.py
src/api/config.py
src/api/main.py
src/api/security.py
src/api/routers/__init__.py
src/api/routers/chat.py
src/api/routers/hed.py
src/cli/__init__.py
src/cli/client.py
src/cli/config.py
src/cli/main.py
src/core/__init__.py
src/core/domain/__init__.py
src/core/services/__init__.py
src/core/services/litellm_llm.py
src/core/services/llm.py
src/interfaces/__init__.py
src/interfaces/protocols.py
src/tools/__init__.py
src/tools/base.py
src/tools/fetcher.py
src/tools/hed.py
src/tools/hed_validation.py
src/tools/markdown_cleaner.py
src/utils/__init__.py
open_science_assistant-0.2.0a0.dist-info/METADATA
open_science_assistant-0.2.0a0.dist-info/WHEEL
open_science_assistant-0.2.0a0.dist-info/entry_points.txt
open_science_assistant-0.2.0a0.dist-info/licenses/LICENSE
open_science_assistant-0.2.0a0.dist-info/RECORD
