Metadata-Version: 2.4
Name: open-science-assistant
Version: 0.2.0a0
Summary: Open Science Assistant - An extensible AI assistant platform for open science projects
Project-URL: Homepage, https://github.com/OpenScience-Collective/osa
Project-URL: Documentation, https://github.com/OpenScience-Collective/osa#readme
Project-URL: Repository, https://github.com/OpenScience-Collective/osa
Project-URL: Issues, https://github.com/OpenScience-Collective/osa/issues
Author: Open Science Collective
Maintainer-email: Yahya Shirazi <yahya@osc.earth>
License: MIT
License-File: LICENSE
Keywords: ai,assistant,bids,eeglab,hed,langchain,langgraph,open-science
Classifier: Development Status :: 3 - Alpha
Classifier: Intended Audience :: Science/Research
Classifier: License :: OSI Approved :: MIT License
Classifier: Programming Language :: Python :: 3
Classifier: Programming Language :: Python :: 3.11
Classifier: Programming Language :: Python :: 3.12
Classifier: Programming Language :: Python :: 3.13
Classifier: Topic :: Scientific/Engineering
Requires-Python: >=3.11
Requires-Dist: beautifulsoup4>=4.14.0
Requires-Dist: fastapi>=0.125.0
Requires-Dist: httpx>=0.28.0
Requires-Dist: langchain-anthropic>=1.3.0
Requires-Dist: langchain-community>=0.4.0
Requires-Dist: langchain-core>=1.2.0
Requires-Dist: langchain-litellm>=0.2.0
Requires-Dist: langchain-openai>=1.1.0
Requires-Dist: langchain>=1.2.0
Requires-Dist: langfuse>=3.11.0
Requires-Dist: langgraph-checkpoint-postgres>=3.0.0
Requires-Dist: langgraph>=1.0.0
Requires-Dist: litellm>=1.50.0
Requires-Dist: lxml>=6.0.0
Requires-Dist: markdownify>=1.1.0
Requires-Dist: platformdirs>=4.5.0
Requires-Dist: psycopg[binary]>=3.3.0
Requires-Dist: pyalex>=0.19
Requires-Dist: pydantic-settings>=2.12.0
Requires-Dist: pydantic>=2.12.0
Requires-Dist: pygithub>=2.8.0
Requires-Dist: python-dotenv>=1.2.0
Requires-Dist: pyyaml>=6.0.3
Requires-Dist: rich>=14.0.0
Requires-Dist: typer>=0.20.0
Requires-Dist: uvicorn[standard]>=0.38.0
Provides-Extra: dev
Requires-Dist: mypy>=1.19.0; extra == 'dev'
Requires-Dist: pre-commit>=4.5.0; extra == 'dev'
Requires-Dist: pytest-asyncio>=1.3.0; extra == 'dev'
Requires-Dist: pytest-cov>=7.0.0; extra == 'dev'
Requires-Dist: pytest>=9.0.0; extra == 'dev'
Requires-Dist: ruff>=0.14.0; extra == 'dev'
Requires-Dist: uv>=0.5.0; extra == 'dev'
